loadshift/__init__.py
loadshift/moving_horizon.py
loadshift/solver_adapters.py
loadshift/time_ranges.py
loadshift/transfer_indices.py
loadshift/utils.py
loadshift/virtual_storage.py
loadshift-0.1.0.dist-info/METADATA
loadshift-0.1.0.dist-info/WHEEL
loadshift-0.1.0.dist-info/licenses/LICENSE
loadshift-0.1.0.dist-info/RECORD
