Metadata-Version: 2.4
Name: loadshift
Version: 0.1.0
Summary: Optimize load shifting based on known prices and a given flexibility level
Project-URL: Homepage, https://github.com/NoviaIntSysGroup/load-shift-optimizer
Project-URL: Repository, https://github.com/NoviaIntSysGroup/load-shift-optimizer
Author-email: Johan Westö <johan.westo@gmail.com>, Hafiz Muhammad Ahmad Imam <ahmadimam657@gmail.com>
License: MIT License
License-File: LICENSE
Requires-Python: >=3.12
Requires-Dist: cffi>=2.0.0
Requires-Dist: mip>=1.14.0
Requires-Dist: numpy>=2.3.5
Requires-Dist: pandas>=2.3.3
Requires-Dist: tqdm>=4.67.1
Provides-Extra: gurobi
Requires-Dist: gurobipy>=13.0.0; extra == 'gurobi'
